parameter_decorators/__init__.py
parameter_decorators/common.py
parameter_decorators/decoration_interface.py
parameter_decorators/decorators/__init__.py
parameter_decorators/decorators/path_to_str.py
parameter_decorators/decorators/str_to_path.py
tests/test_path_to_str.py
tests/test_str_to_path.py
parameter_decorators-0.0.2.dist-info/LICENSE
parameter_decorators-0.0.2.dist-info/METADATA
parameter_decorators-0.0.2.dist-info/WHEEL
parameter_decorators-0.0.2.dist-info/top_level.txt
parameter_decorators-0.0.2.dist-info/RECORD
