Metadata-Version: 2.1
Name: parameter-decorators
Version: 0.0.2
Summary: Handy decorators for converting parameters
Author: Matan Perelman
Author-email: matan1008@gmail.com
License:                     GNU GENERAL PUBLIC LICENSE
Project-URL: Homepage, https://github.com/matan1008/parameter-decorators
Project-URL: Source, https://github.com/matan1008/parameter-decorators
Classifier: Programming Language :: Python :: 3.7
Classifier: Programming Language :: Python :: 3.8
Classifier: Programming Language :: Python :: 3.9
Classifier: Programming Language :: Python :: 3.10
Classifier: Programming Language :: Python :: 3.11
Requires-Python: >=3.7
Provides-Extra: testing
License-File: LICENSE
